buser_django_instrumentation_sentry/__init__.py
buser_django_instrumentation_sentry/middleware.py
buser_django_instrumentation_sentry/redis_dedup_integration.py
buser_django_instrumentation_sentry/sanitize.py
buser_django_instrumentation_sentry-0.0.1.dist-info/METADATA
buser_django_instrumentation_sentry-0.0.1.dist-info/WHEEL
buser_django_instrumentation_sentry-0.0.1.dist-info/top_level.txt
buser_django_instrumentation_sentry-0.0.1.dist-info/RECORD
