Metadata-Version: 2.1
Name: buser-django-instrumentation-sentry
Version: 0.0.1
Summary: A helper library to configure centry instrumentation in Django projects.
Home-page: http://packages.python.org/buser-django-instrumentation-sentry
Author: Erle Carrara
Author-email: erle.carrara@buser.com.br
License: MIT
Keywords: buser sentry django
Platform: UNKNOWN
Classifier: Development Status :: 3 - Alpha
Classifier: Topic :: Utilities
Classifier: License :: OSI Approved :: MIT License
Requires-Dist: django (<4)
Requires-Dist: raven (<7)
Requires-Dist: sentry-sdk (<2)
Provides-Extra: redis_dedup
Requires-Dist: redis (<5) ; extra == 'redis_dedup'
